fastgwr/FastGWR.py
fastgwr/FastMGWR.py
fastgwr/__init__.py
fastgwr/__main__.py
fastgwr/fastgwr_mpi.py
fastgwr-0.2.9.dist-info/LICENSE.md
fastgwr-0.2.9.dist-info/METADATA
fastgwr-0.2.9.dist-info/WHEEL
fastgwr-0.2.9.dist-info/dependency_links.txt
fastgwr-0.2.9.dist-info/entry_points.txt
fastgwr-0.2.9.dist-info/top_level.txt
fastgwr-0.2.9.dist-info/RECORD
