Metadata-Version: 2.1
Name: fastgwr
Version: 0.2.9
Summary: Fast Parallel Computation of Geographically Weighted Regression
Home-page: https://github.com/Ziqi-Li/FastGWR
Author: Ziqi Li
Author-email: liziqi1992@gmail.com
License: MIT
Platform: UNKNOWN
Classifier: License :: OSI Approved :: MIT License
Classifier: Programming Language :: Python :: 2.7
Classifier: Programming Language :: Python :: 3
Classifier: Programming Language :: Python :: 3.7
Requires-Dist: mpi4py
Requires-Dist: scipy
Requires-Dist: numpy
Requires-Dist: click
Requires-Dist: twine
